rmq_broker/__init__.py
rmq_broker/models.py
rmq_broker/schemas.py
rmq_broker/settings.py
rmq_broker/async_chains/__init__.py
rmq_broker/async_chains/base.py
rmq_broker/chains/__init__.py
rmq_broker/chains/base.py
rmq_broker/documentation/__init__.py
rmq_broker/documentation/base.py
rmq_broker/documentation/models.py
rmq_broker/documentation/utils.py
rmq_broker/documentation/mixins/__init__.py
rmq_broker/documentation/mixins/pydantic/__init__.py
rmq_broker/documentation/mixins/pydantic/chains.py
rmq_broker/documentation/mixins/pydantic/utils.py
rmq_broker/queues/__init__.py
rmq_broker/queues/base.py
rmq_broker/queues/rabbitmq.py
rmq_broker/services/__init__.py
rmq_broker/services/base.py
rmq_broker/tests/__init__.py
rmq_broker/tests/factories.py
rmq_broker/tests/test_models.py
rmq_broker/utils/__init__.py
rmq_broker/utils/singleton.py
rabbitmq_broker-1.2.6.dist-info/LICENSE
rabbitmq_broker-1.2.6.dist-info/METADATA
rabbitmq_broker-1.2.6.dist-info/WHEEL
rabbitmq_broker-1.2.6.dist-info/top_level.txt
rabbitmq_broker-1.2.6.dist-info/RECORD
