Metadata-Version: 2.2
Name: rabbitmq-broker
Version: 1.2.6
Summary: RPC брокер сообщений
Author-email: Nikita Sysoev <njt55cs@gmail.com>
Project-URL: Homepage, https://github.com/nylinary/rabbitmq-broker
Project-URL: Repository, https://github.com/nylinary/rabbitmq-broker
Project-URL: Issues, https://github.com/nylinary/rabbitmq-broker/issues
Classifier: Programming Language :: Python :: 3
Classifier: License :: OSI Approved :: MIT License
Classifier: Operating System :: OS Independent
Requires-Python: >=3.9
License-File: LICENSE
Requires-Dist: aio-pika~=9.0.2
Requires-Dist: django-environ~=0.9.0
Requires-Dist: starlette~=0.25.0
Requires-Dist: webportal-utils>=0.1.1
